{"labelsByUnit":{"0":["noise"],"1":["noise"],"108":["noise"],"11":["noise"],"110":["noise"],"114":["noise"],"123":["noise"],"129":["noise"],"13":["noise"],"131":["noise"],"132":["noise"],"133":["noise"],"14":["noise"],"140":["noise"],"15":["noise"],"152":["noise"],"16":["noise"],"17":["noise"],"18":["noise"],"20":["noise"],"34":["noise"],"39":["noise"],"4":["noise"],"45":["noise"],"48":["noise"],"5":["noise"],"51":["noise"],"55":["noise"],"57":["noise"],"58":["noise"],"59":["noise"],"6":["noise"],"60":["noise"],"61":["noise"],"62":["noise"],"63":["noise"],"64":["noise"],"67":["noise"],"68":["noise"],"69":["noise"],"7":["noise"],"73":["noise"],"74":["noise"],"75":["noise"],"78":["noise"],"8":["noise"],"80":["noise"],"83":["noise"],"9":["noise"],"93":["noise"],"95":["noise"]}}